twapp/__init__.py
twapp/main.py
twapp/shelves/twapp/Makefile
twapp/shelves/twapp/README.md
twapp/shelves/twapp/setup.py
twapp/shelves/twapp/config/logging.conf
twapp/shelves/twapp/src/twapp/__init__.py
twapp/shelves/twapp/src/twapp/main.py
twapp/shelves/twapp/src/twapp/api/__init__.py
twapp/shelves/twapp/src/twapp/api/urls.py
twapp/shelves/twapp/src/twapp/api/handlers/__init__.py
twapp/shelves/twapp/src/twapp/api/handlers/index.py
twapp/shelves/twapp/src/twapp/controllers/__init__.py
twapp/shelves/twapp/src/twapp/controllers/api.py
twapp-0.0.3.dist-info/DESCRIPTION.rst
twapp-0.0.3.dist-info/METADATA
twapp-0.0.3.dist-info/RECORD
twapp-0.0.3.dist-info/WHEEL
twapp-0.0.3.dist-info/entry_points.txt
twapp-0.0.3.dist-info/metadata.json
twapp-0.0.3.dist-info/top_level.txt
