Metadata-Version: 2.0
Name: twapp
Version: 0.0.3
Summary: tornado web app generator
Home-page: https://github.com/liujinliu/twapp
Author: liujinliu
Author-email: liujinliu@lbesec.com
License: UNKNOWN
Platform: UNKNOWN
Classifier: Environment :: Console
Classifier: Topic :: Utilities
Requires-Dist: tornado
